cheval/__init__.py
cheval-22.4.0.dist-info/LICENSE
cheval-22.4.0.dist-info/METADATA
cheval-22.4.0.dist-info/WHEEL
cheval-22.4.0.dist-info/top_level.txt
cheval-22.4.0.dist-info/RECORD
