Metadata-Version: 2.1
Name: cheval
Version: 22.4.0
Summary: TBC
Home-page: https://github.com/rpeloff/cheval
Author: Ryan Eloff
Author-email: ryaneloff@gmail.com
Maintainer: Ryan Eloff
Maintainer-email: ryaneloff@gmail.com
License: Apache-2.0
Project-URL: Source Code, https://github.com/rpeloff/cheval
Keywords: machine learning
Platform: UNKNOWN
Classifier: Development Status :: 2 - Pre-Alpha
Classifier: Intended Audience :: Developers
Classifier: Natural Language :: English
Classifier: License :: OSI Approved :: Apache Software License
Classifier: Operating System :: OS Independent
Classifier: Programming Language :: Python
Classifier: Programming Language :: Python :: 3
Classifier: Programming Language :: Python :: 3.6
Classifier: Programming Language :: Python :: 3.7
Classifier: Programming Language :: Python :: 3.8
Classifier: Programming Language :: Python :: 3.9
Classifier: Programming Language :: Python :: 3.10
Classifier: Programming Language :: Python :: Implementation :: CPython
Classifier: Programming Language :: Python :: Implementation :: PyPy
Classifier: Topic :: Software Development :: Libraries :: Python Modules
Requires-Python: >=3.6
License-File: LICENSE
